<?xml version="1.0" encoding="UTF-8"?>
<Index xmlns="http://www.tso.co.uk/assets/namespace/gazetteindex" editionCode="L" page="034" pageID="https://www.thegazette.co.uk/id/London/index/year/1968/volume/4/page/034" pagePDF="https://www.thegazette.co.uk/London/index/year/1968/volume/4/page/034" pageRDF="https://www.thegazette.co.uk/London/index/year/1968/volume/4/page/034?view=linked-data" type="index" volume="4" year="1968">
  <ItemGroup>
    <MainItem>
      <Key>Rosine</Key>
      <Forenames>J</Forenames>
      <PageNumber>11049</PageNumber>
    </MainItem>
  </ItemGroup>
  <ItemGroup>
    <MainItem>
      <Key>Ross</Key>
      <Forenames>D. J</Forenames>
      <PageNumber>11327</PageNumber>
    </MainItem>
  </ItemGroup>
  <ItemGroup>
    <MainItem>
      <Key>
        <KeyDitto>___ ___ ___</KeyDitto>
      </Key>
      <Forenames>D. L</Forenames>
      <PageNumber>12942</PageNumber>
    </MainItem>
  </ItemGroup>
  <ItemGroup>
    <MainItem>
      <Key>
        <KeyDitto>___ ___ ___</KeyDitto>
      </Key>
      <Forenames>G. H</Forenames>
      <PageNumber>13225</PageNumber>
    </MainItem>
  </ItemGroup>
  <ItemGroup>
    <MainItem>
      <Key>
        <KeyDitto>___ ___ ___ ___</KeyDitto>
      </Key>
      <Forenames>P. B. T.</Forenames>
      <PageNumber>10530</PageNumber>
    </MainItem>
  </ItemGroup>
  <ItemGroup>
    <MainItem>
      <Key>
        <KeyDitto>___ ___ ___</KeyDitto>
      </Key>
      <Forenames>T. A</Forenames>
      <PageNumber>13917</PageNumber>
    </MainItem>
  </ItemGroup>
  <ItemGroup>
    <MainItem>
      <Key>Ross-Jones</Key>
      <Forenames>W. J. C.</Forenames>
      <PageNumber>12122</PageNumber>
    </MainItem>
  </ItemGroup>
  <ItemGroup>
    <MainItem>
      <Key>Rossiter</Key>
      <Forenames>J. M.</Forenames>
      <PageNumber>12123</PageNumber>
    </MainItem>
  </ItemGroup>
  <ItemGroup>
    <MainItem>
      <Key>
        <KeyDitto>___ ___ ___</KeyDitto>
      </Key>
      <Forenames>R. E</Forenames>
      <PageNumber>10771</PageNumber>
    </MainItem>
  </ItemGroup>
  <ItemGroup>
    <MainItem>
      <Key>Rothery</Key>
      <Forenames>D. J.</Forenames>
      <PageNumber>11323</PageNumber>
    </MainItem>
  </ItemGroup>
  <ItemGroup>
    <MainItem>
      <Key>Rothwell</Key>
      <Forenames>D. M.</Forenames>
      <PageNumber>13794</PageNumber>
    </MainItem>
  </ItemGroup>
  <ItemGroup>
    <MainItem>
      <Key>
        <KeyDitto>___ ___</KeyDitto>
      </Key>
      <Forenames>G. K.</Forenames>
      <PageNumber>12118</PageNumber>
    </MainItem>
  </ItemGroup>
  <ItemGroup>
    <MainItem>
      <Key>
        <KeyDitto>___ ___ ___ ___</KeyDitto>
      </Key>
      <Forenames>J. R</Forenames>
      <PageNumber>10529</PageNumber>
    </MainItem>
  </ItemGroup>
  <ItemGroup>
    <MainItem>
      <Key>RoXsey</Key>
      <Forenames>C. M.</Forenames>
      <PageNumber>11846</PageNumber>
    </MainItem>
  </ItemGroup>
  <ItemGroup>
    <MainItem>
      <Key>Roualle</Key>
      <Forenames>E. M.</Forenames>
      <PageNumber>10532</PageNumber>
    </MainItem>
  </ItemGroup>
  <ItemGroup>
    <MainItem>
      <Key>Rough</Key>
      <Forenames>M. J. A.</Forenames>
      <PageNumber>13230</PageNumber>
    </MainItem>
  </ItemGroup>
  <ItemGroup>
    <MainItem>
      <Key>Rough</Key>
      <Text>ton, J. F. W</Text>
      <PageNumber>12667</PageNumber>
    </MainItem>
  </ItemGroup>
  <ItemGroup>
    <MainItem>
      <Key>
        <KeyDitto>___ ___ ___</KeyDitto>
      </Key>
      <Forenames>M. G</Forenames>
      <PageNumber>12408</PageNumber>
    </MainItem>
  </ItemGroup>
  <ItemGroup>
    <MainItem>
      <Key>Roulinson</Key>
      <Forenames>D. E.</Forenames>
      <PageNumber>12947</PageNumber>
    </MainItem>
  </ItemGroup>
  <ItemGroup>
    <MainItem>
      <Key>Roulstone</Key>
      <Forenames>A. R. M.</Forenames>
      <PageNumber>11327</PageNumber>
    </MainItem>
  </ItemGroup>
  <ItemGroup>
    <MainItem>
      <Key>Rouseffl</Key>
      <Forenames>R. H.</Forenames>
      <PageNumber>11328</PageNumber>
    </MainItem>
  </ItemGroup>
  <ItemGroup>
    <MainItem>
      <Key>Rowbottom</Key>
      <Forenames>K. J.</Forenames>
      <PageNumber>11327</PageNumber>
    </MainItem>
  </ItemGroup>
  <ItemGroup>
    <MainItem>
      <Key>Rowden</Key>
      <Forenames>A.</Forenames>
      <PageNumber>13916</PageNumber>
    </MainItem>
  </ItemGroup>
  <ItemGroup>
    <MainItem>
      <Key>Rowe</Key>
      <Forenames>B</Forenames>
      <PageNumber>10774</PageNumber>
    </MainItem>
  </ItemGroup>
  <ItemGroup>
    <MainItem>
      <Key>
        <KeyDitto>___ ___ ___</KeyDitto>
      </Key>
      <Forenames>J. C. P.</Forenames>
      <PageNumber>13509</PageNumber>
      <PageNumber>13513</PageNumber>
    </MainItem>
  </ItemGroup>
  <ItemGroup>
    <MainItem>
      <Key>
        <KeyDitto>___ ___ ___</KeyDitto>
      </Key>
      <Forenames>K. W.</Forenames>
      <PageNumber>11585</PageNumber>
    </MainItem>
  </ItemGroup>
  <ItemGroup>
    <MainItem>
      <Key>
        <KeyDitto>___ ___</KeyDitto>
      </Key>
      <Forenames>N. A.</Forenames>
      <PageNumber>11322</PageNumber>
    </MainItem>
  </ItemGroup>
  <ItemGroup>
    <MainItem>
      <Key>
        <KeyDitto>___ ___</KeyDitto>
      </Key>
      <Forenames>R. G.</Forenames>
      <PageNumber>11327</PageNumber>
    </MainItem>
  </ItemGroup>
  <ItemGroup>
    <MainItem>
      <Key>
        <KeyDitto>___</KeyDitto>
      </Key>
      <Forenames>V. N.</Forenames>
      <PageNumber>11322</PageNumber>
    </MainItem>
  </ItemGroup>
  <ItemGroup>
    <MainItem>
      <Key>Rowland</Key>
      <Forenames>A. D.</Forenames>
      <PageNumber>11054</PageNumber>
    </MainItem>
  </ItemGroup>
  <ItemGroup>
    <MainItem>
      <Key>
        <KeyDitto>___ ___</KeyDitto>
      </Key>
      <Forenames>J.</Forenames>
      <PageNumber>13912</PageNumber>
    </MainItem>
  </ItemGroup>
  <ItemGroup>
    <MainItem>
      <Key>Rowlands</Key>
      <Forenames>H.</Forenames>
      <PageNumber>12402</PageNumber>
    </MainItem>
  </ItemGroup>
  <ItemGroup>
    <MainItem>
      <Key>Rowley</Key>
      <Forenames>G. J.</Forenames>
      <PageNumber>11321</PageNumber>
    </MainItem>
  </ItemGroup>
  <ItemGroup>
    <MainItem>
      <Key>
        <KeyDitto>___ ___ ___</KeyDitto>
      </Key>
      <Forenames>R. A.</Forenames>
      <PageNumber>12667</PageNumber>
    </MainItem>
  </ItemGroup>
  <ItemGroup>
    <MainItem>
      <Key>Rowson</Key>
      <Forenames>W. C.</Forenames>
      <PageNumber>10535</PageNumber>
    </MainItem>
  </ItemGroup>
  <ItemGroup>
    <MainItem>
      <Key>Roy</Key>
      <Forenames>E. W. D.</Forenames>
      <PageNumber>11051</PageNumber>
    </MainItem>
  </ItemGroup>
  <ItemGroup>
    <MainItem>
      <Key>Roycroft</Key>
      <Forenames>D. A.</Forenames>
      <PageNumber>13509</PageNumber>
    </MainItem>
  </ItemGroup>
  <ItemGroup>
    <MainItem>
      <Key>
        <KeyDitto>___ ___ ___</KeyDitto>
      </Key>
      <Forenames>S. E.</Forenames>
      <PageNumber>10777</PageNumber>
      <PageNumber>13779</PageNumber>
    </MainItem>
  </ItemGroup>
  <ItemGroup>
    <MainItem>
      <Key>Royston</Key>
      <Forenames>P. R.</Forenames>
      <PageNumber>13909</PageNumber>
    </MainItem>
  </ItemGroup>
  <ItemGroup>
    <MainItem>
      <Key>Roythorne</Key>
      <Forenames>M. E.</Forenames>
      <PageNumber>11581</PageNumber>
    </MainItem>
  </ItemGroup>
  <ItemGroup>
    <MainItem>
      <Key>Rucker</Key>
      <Forenames>J. W. F.</Forenames>
      <PageNumber>13911</PageNumber>
    </MainItem>
  </ItemGroup>
  <ItemGroup>
    <MainItem>
      <Key>Rudd</Key>
      <Forenames>D. H. C.</Forenames>
      <PageNumber>12405</PageNumber>
    </MainItem>
  </ItemGroup>
  <ItemGroup>
    <MainItem>
      <Key>Ruddy</Key>
      <Forenames>B. A.</Forenames>
      <PageNumber>13914</PageNumber>
    </MainItem>
  </ItemGroup>
  <ItemGroup>
    <MainItem>
      <Key>Rudrabahadur</Key>
      <Forenames>Chhetri</Forenames>
      <PageNumber>11050</PageNumber>
    </MainItem>
  </ItemGroup>
  <ItemGroup>
    <MainItem>
      <Key>Rudram</Key>
      <Forenames>L. W.</Forenames>
      <PageNumber>12671</PageNumber>
    </MainItem>
  </ItemGroup>
  <ItemGroup>
    <MainItem>
      <Key>Ruel</Key>
      <Forenames>K. B.</Forenames>
      <PageNumber>10771</PageNumber>
    </MainItem>
  </ItemGroup>
  <ItemGroup>
    <MainItem>
      <Key>Rugg-Gunn</Key>
      <Forenames>A. J.</Forenames>
      <PageNumber>11840</PageNumber>
    </MainItem>
  </ItemGroup>
  <ItemGroup>
    <MainItem>
      <Key>Rumble</Key>
      <Forenames>B. C.</Forenames>
      <PageNumber>12666</PageNumber>
    </MainItem>
  </ItemGroup>
  <ItemGroup>
    <MainItem>
      <Key>
        <KeyDitto>___ ___</KeyDitto>
      </Key>
      <Forenames>R. R. W.</Forenames>
      <PageNumber>13907</PageNumber>
    </MainItem>
  </ItemGroup>
  <ItemGroup>
    <MainItem>
      <Key>Rumsey</Key>
      <Forenames>A. V.</Forenames>
      <PageNumber>11840</PageNumber>
    </MainItem>
  </ItemGroup>
  <ItemGroup>
    <MainItem>
      <Key>Rundle</Key>
      <Forenames>T. J.</Forenames>
      <PageNumber>12119</PageNumber>
    </MainItem>
  </ItemGroup>
  <ItemGroup>
    <MainItem>
      <Key>Rush</Key>
      <Forenames>J</Forenames>
      <PageNumber>12402</PageNumber>
    </MainItem>
  </ItemGroup>
  <ItemGroup>
    <MainItem>
      <Key>Rushton</Key>
      <Forenames>M. M.</Forenames>
      <PageNumber>10774</PageNumber>
    </MainItem>
  </ItemGroup>
  <ItemGroup>
    <MainItem>
      <Key>Rushworth</Key>
      <Forenames>G. M.</Forenames>
      <PageNumber>13794</PageNumber>
    </MainItem>
  </ItemGroup>
  <ItemGroup>
    <MainItem>
      <Key>
        <KeyDitto>___ ___</KeyDitto>
      </Key>
      <Forenames>T. P</Forenames>
      <PageNumber>11844</PageNumber>
    </MainItem>
  </ItemGroup>
  <ItemGroup>
    <MainItem>
      <Key>Russeil</Key>
      <Forenames>C. P. B.</Forenames>
      <PageNumber>12407</PageNumber>
    </MainItem>
  </ItemGroup>
  <ItemGroup>
    <MainItem>
      <Key>
        <KeyDitto>___ ___</KeyDitto>
      </Key>
      <Forenames>F. P</Forenames>
      <PageNumber>10776</PageNumber>
    </MainItem>
  </ItemGroup>
  <ItemGroup>
    <MainItem>
      <Key>
        <KeyDitto>___ ___</KeyDitto>
      </Key>
      <Forenames>J. R</Forenames>
      <PageNumber>11840</PageNumber>
    </MainItem>
  </ItemGroup>
  <ItemGroup>
    <MainItem>
      <Key>
        <KeyDitto>___ ___</KeyDitto>
      </Key>
      <Forenames>M. R</Forenames>
      <PageNumber>13232</PageNumber>
    </MainItem>
  </ItemGroup>
  <ItemGroup>
    <MainItem>
      <Key>
        <KeyDitto>___ ___</KeyDitto>
      </Key>
      <Forenames>R</Forenames>
      <PageNumber>10771</PageNumber>
    </MainItem>
  </ItemGroup>
  <ItemGroup>
    <MainItem>
      <Key>
        <KeyDitto>___ ___</KeyDitto>
      </Key>
      <Text>j</Text>
      <PageNumber>13795</PageNumber>
    </MainItem>
  </ItemGroup>
  <ItemGroup>
    <MainItem>
      <Key>Russell-Tories</Key>
      <Forenames>P. J.</Forenames>
      <PageNumber>11326</PageNumber>
    </MainItem>
  </ItemGroup>
  <ItemGroup>
    <MainItem>
      <Key>Russell-Smith</Key>
      <Forenames>D.</Forenames>
      <PageNumber>10774</PageNumber>
    </MainItem>
  </ItemGroup>
  <ItemGroup>
    <MainItem>
      <Key>Rutherford</Key>
      <Forenames>B. H.</Forenames>
      <PageNumber>10771</PageNumber>
    </MainItem>
  </ItemGroup>
  <ItemGroup>
    <MainItem>
      <Key>
        <KeyDitto>___ ___ ___</KeyDitto>
      </Key>
      <Forenames>T. B</Forenames>
      <PageNumber>13917</PageNumber>
    </MainItem>
  </ItemGroup>
  <ItemGroup>
    <MainItem>
      <Key>
        <KeyDitto>___ ___</KeyDitto>
      </Key>
      <Forenames>R. F</Forenames>
      <PageNumber>11326</PageNumber>
    </MainItem>
  </ItemGroup>
  <ItemGroup>
    <MainItem>
      <Key>
        <KeyDitto>___ ___ ___</KeyDitto>
      </Key>
      <Forenames>R. S. A.</Forenames>
      <PageNumber>11050</PageNumber>
    </MainItem>
  </ItemGroup>
  <ItemGroup>
    <MainItem>
      <Key>Ruthven</Key>
      <Forenames>T. C.</Forenames>
      <PageNumber>13513</PageNumber>
    </MainItem>
  </ItemGroup>
  <ItemGroup>
    <MainItem>
      <Key>Ryan</Key>
      <Forenames>A. G.</Forenames>
      <PageNumber>11330</PageNumber>
    </MainItem>
  </ItemGroup>
  <ItemGroup>
    <MainItem>
      <Key>
        <KeyDitto>___ ___</KeyDitto>
      </Key>
      <Forenames>B. P.</Forenames>
      <Text>DA</Text>
      <PageNumber>11842</PageNumber>
    </MainItem>
  </ItemGroup>
  <ItemGroup>
    <MainItem>
      <Key>
        <KeyDitto>___ ___</KeyDitto>
      </Key>
      <Forenames>D. C</Forenames>
      <PageNumber>13228</PageNumber>
    </MainItem>
  </ItemGroup>
  <ItemGroup>
    <MainItem>
      <Key>
        <KeyDitto>___ ___</KeyDitto>
      </Key>
      <Forenames>D. E</Forenames>
      <PageNumber>13911</PageNumber>
    </MainItem>
  </ItemGroup>
  <ItemGroup>
    <MainItem>
      <Key>
        <KeyDitto>___ ___</KeyDitto>
      </Key>
      <Forenames>T. F</Forenames>
      <PageNumber>11839</PageNumber>
    </MainItem>
  </ItemGroup>
  <ItemGroup>
    <MainItem>
      <Key>
        <KeyDitto>___</KeyDitto>
      </Key>
      <Forenames>M. W.</Forenames>
      <PageNumber>13917</PageNumber>
    </MainItem>
  </ItemGroup>
  <ItemGroup>
    <MainItem>
      <Key>Rycroft</Key>
      <Forenames>C. I.</Forenames>
      <PageNumber>11326</PageNumber>
    </MainItem>
  </ItemGroup>
  <ItemGroup>
    <MainItem>
      <Key>
        <KeyDitto>___ ___</KeyDitto>
      </Key>
      <Forenames>N. D</Forenames>
      <PageNumber>12122</PageNumber>
    </MainItem>
  </ItemGroup>
  <ItemGroup>
    <MainItem>
      <Key>Ryman</Key>
      <Forenames>R. W. J.</Forenames>
      <PageNumber>13913</PageNumber>
    </MainItem>
  </ItemGroup>
  <ItemGroup>
    <MainItem>
      <Key>Sadler</Key>
      <Forenames>G</Forenames>
      <PageNumber>10777</PageNumber>
    </MainItem>
  </ItemGroup>
  <ItemGroup>
    <MainItem>
      <Key>
        <KeyDitto>___ ___ ___</KeyDitto>
      </Key>
      <Forenames>T. T. S.</Forenames>
      <PageNumber>10777</PageNumber>
    </MainItem>
  </ItemGroup>
  <ItemGroup>
    <MainItem>
      <Key>St</Key>
      <Forenames>John</Forenames>
      <Text>, J. L</Text>
      <PageNumber>12668</PageNumber>
    </MainItem>
  </ItemGroup>
  <ItemGroup>
    <MainItem>
      <Key>St</Key>
      <Forenames>Ruth</Forenames>
      <Text>, P</Text>
      <PageNumber>11842</PageNumber>
    </MainItem>
  </ItemGroup>
  <ItemGroup>
    <MainItem>
      <Key>St</Key>
      <Forenames>Vaughan</Forenames>
      <Text>, T. E. J</Text>
      <PageNumber>10772</PageNumber>
    </MainItem>
  </ItemGroup>
  <ItemGroup>
    <MainItem>
      <Key>Saker</Key>
      <Forenames>R. G.</Forenames>
      <PageNumber>11840</PageNumber>
      <PageNumber>13508</PageNumber>
    </MainItem>
  </ItemGroup>
  <ItemGroup>
    <MainItem>
      <Key>Salkeld</Key>
      <Forenames>P. I.</Forenames>
      <PageNumber>11839</PageNumber>
    </MainItem>
  </ItemGroup>
  <ItemGroup>
    <MainItem>
      <Key>Salmon</Key>
      <Forenames>R.</Forenames>
      <PageNumber>10534</PageNumber>
    </MainItem>
  </ItemGroup>
  <ItemGroup>
    <MainItem>
      <Key>
        <KeyDitto>___ ___ ___ ___</KeyDitto>
      </Key>
      <Forenames>W. B.</Forenames>
      <PageNumber>13794</PageNumber>
    </MainItem>
  </ItemGroup>
  <ItemGroup>
    <MainItem>
      <Key>Saltmarsh</Key>
      <Forenames>J. B.</Forenames>
      <PageNumber>12408</PageNumber>
    </MainItem>
  </ItemGroup>
  <ItemGroup>
    <MainItem>
      <Key>Sampson</Key>
      <Forenames>A. J.</Forenames>
      <PageNumber>13914</PageNumber>
    </MainItem>
  </ItemGroup>
  <ItemGroup>
    <MainItem>
      <Key>Samuel</Key>
      <Forenames>M. D.</Forenames>
      <PageNumber>13914</PageNumber>
    </MainItem>
  </ItemGroup>
  <ItemGroup>
    <MainItem>
      <Key>Samways</Key>
      <Forenames>N. J.</Forenames>
      <PageNumber>12118</PageNumber>
    </MainItem>
  </ItemGroup>
  <ItemGroup>
    <MainItem>
      <Key>Sanders</Key>
      <Forenames>C. A.</Forenames>
      <PageNumber>11581</PageNumber>
    </MainItem>
  </ItemGroup>
  <ItemGroup>
    <MainItem>
      <Key>Sanderson</Key>
      <Forenames>J. B.</Forenames>
      <PageNumber>13227</PageNumber>
    </MainItem>
  </ItemGroup>
  <ItemGroup>
    <MainItem>
      <Key>
        <KeyDitto>___ ___</KeyDitto>
      </Key>
      <Forenames>J. M.</Forenames>
      <PageNumber>11848</PageNumber>
    </MainItem>
  </ItemGroup>
  <ItemGroup>
    <MainItem>
      <Key>
        <KeyDitto>___ ___</KeyDitto>
      </Key>
      <Forenames>T. A.</Forenames>
      <PageNumber>11843</PageNumber>
    </MainItem>
  </ItemGroup>
  <ItemGroup>
    <MainItem>
      <Key>Sandoe</Key>
      <Forenames>R. J.</Forenames>
      <PageNumber>11587</PageNumber>
    </MainItem>
  </ItemGroup>
  <ItemGroup>
    <MainItem>
      <Key>Sands</Key>
      <Forenames>R.</Forenames>
      <PageNumber>11322</PageNumber>
    </MainItem>
  </ItemGroup>
  <ItemGroup>
    <MainItem>
      <Key>Sandys</Key>
      <Forenames>J. G. W.</Forenames>
      <PageNumber>11841</PageNumber>
    </MainItem>
  </ItemGroup>
  <ItemGroup>
    <MainItem>
      <Key>Sanford</Key>
      <Forenames>I. J.</Forenames>
      <PageNumber>11586</PageNumber>
    </MainItem>
  </ItemGroup>
  <ItemGroup>
    <MainItem>
      <Key>Sanger-Davies</Key>
      <Forenames>M.</Forenames>
      <PageNumber>10777</PageNumber>
    </MainItem>
  </ItemGroup>
  <ItemGroup>
    <MainItem>
      <Key>Sansome</Key>
      <Forenames>R. S.</Forenames>
      <PageNumber>12947</PageNumber>
    </MainItem>
  </ItemGroup>
  <ItemGroup>
    <MainItem>
      <Key>Sant</Key>
      <Forenames>E. W.</Forenames>
      <PageNumber>13796</PageNumber>
    </MainItem>
  </ItemGroup>
  <ItemGroup>
    <MainItem>
      <Key>Sarson</Key>
      <Forenames>F. G.</Forenames>
      <PageNumber>11049</PageNumber>
    </MainItem>
  </ItemGroup>
  <ItemGroup>
    <MainItem>
      <Key>Satow</Key>
      <Forenames>N. C. F.</Forenames>
      <PageNumber>10773</PageNumber>
    </MainItem>
  </ItemGroup>
  <ItemGroup>
    <MainItem>
      <Key>Satvinder</Key>
      <Forenames>Singh Roy</Forenames>
      <PageNumber>13229</PageNumber>
    </MainItem>
  </ItemGroup>
  <ItemGroup>
    <MainItem>
      <Key>Saul</Key>
      <Forenames>A. J. R.</Forenames>
      <PageNumber>11843</PageNumber>
    </MainItem>
  </ItemGroup>
  <ItemGroup>
    <MainItem>
      <Key>Saunders</Key>
      <Forenames>A. D. R.</Forenames>
      <PageNumber>11841</PageNumber>
    </MainItem>
  </ItemGroup>
  <ItemGroup>
    <MainItem>
      <Key>
        <KeyDitto>___ ___</KeyDitto>
      </Key>
      <Forenames>A. F</Forenames>
      <PageNumber>11845</PageNumber>
    </MainItem>
  </ItemGroup>
  <ItemGroup>
    <MainItem>
      <Key>
        <KeyDitto>___ ___</KeyDitto>
      </Key>
      <Forenames>D. J</Forenames>
      <PageNumber>11054</PageNumber>
    </MainItem>
  </ItemGroup>
  <ItemGroup>
    <MainItem>
      <Key>
        <KeyDitto>___ ___ ___</KeyDitto>
      </Key>
      <Forenames>D. M. St</Forenames>
      <Text>. G</Text>
      <PageNumber>11842</PageNumber>
    </MainItem>
  </ItemGroup>
  <ItemGroup>
    <MainItem>
      <Key>
        <KeyDitto>___ ___ ___</KeyDitto>
      </Key>
      <Forenames>M. B</Forenames>
      <PageNumber>11584</PageNumber>
    </MainItem>
  </ItemGroup>
  <ItemGroup>
    <MainItem>
      <Key>
        <KeyDitto>___ ___</KeyDitto>
      </Key>
      <Forenames>M. J</Forenames>
      <PageNumber>11322</PageNumber>
    </MainItem>
  </ItemGroup>
  <ItemGroup>
    <MainItem>
      <Key>
        <KeyDitto>___ ___</KeyDitto>
      </Key>
      <Forenames>O. A</Forenames>
      <PageNumber>11839</PageNumber>
    </MainItem>
  </ItemGroup>
  <ItemGroup>
    <MainItem>
      <Key>
        <KeyDitto>___ ___</KeyDitto>
      </Key>
      <Forenames>W. S</Forenames>
      <PageNumber>13229</PageNumber>
    </MainItem>
  </ItemGroup>
  <ItemGroup>
    <MainItem>
      <Key>Sauzier</Key>
      <Forenames>B. J. L.</Forenames>
      <PageNumber>11327</PageNumber>
    </MainItem>
  </ItemGroup>
  <ItemGroup>
    <MainItem>
      <Key>Savile</Key>
      <Forenames>R</Forenames>
      <PageNumber>10773</PageNumber>
    </MainItem>
  </ItemGroup>
  <ItemGroup>
    <MainItem>
      <Key>Savin</Key>
      <Forenames>J. A.</Forenames>
      <PageNumber>12402</PageNumber>
    </MainItem>
  </ItemGroup>
  <ItemGroup>
    <MainItem>
      <Key>Sawyer</Key>
      <Forenames>A.</Forenames>
      <PageNumber>13227</PageNumber>
    </MainItem>
  </ItemGroup>
  <ItemGroup>
    <MainItem>
      <Key>Scatchard</Key>
      <Forenames>M. A.</Forenames>
      <PageNumber>11322</PageNumber>
    </MainItem>
  </ItemGroup>
  <ItemGroup>
    <MainItem>
      <Key>Schreuder</Key>
      <Forenames>J.</Forenames>
      <PageNumber>11327</PageNumber>
    </MainItem>
  </ItemGroup>
  <ItemGroup>
    <MainItem>
      <Key>Schwartz</Key>
      <Forenames>M. R.</Forenames>
      <PageNumber>12670</PageNumber>
    </MainItem>
  </ItemGroup>
  <ItemGroup>
    <MainItem>
      <Key>Scogings</Key>
      <Forenames>J. C. G.</Forenames>
      <PageNumber>11326</PageNumber>
    </MainItem>
  </ItemGroup>
  <ItemGroup>
    <MainItem>
      <Key>Scorse</Key>
      <Forenames>J. W.</Forenames>
      <PageNumber>13226</PageNumber>
    </MainItem>
  </ItemGroup>
  <ItemGroup>
    <MainItem>
      <Key>Scotford</Key>
      <Forenames>B. L.</Forenames>
      <PageNumber>10778</PageNumber>
    </MainItem>
  </ItemGroup>
  <ItemGroup>
    <MainItem>
      <Key>Scott</Key>
      <Forenames>A</Forenames>
      <PageNumber>12942</PageNumber>
    </MainItem>
  </ItemGroup>
  <ItemGroup>
    <MainItem>
      <Key>
        <KeyDitto>___ ___</KeyDitto>
      </Key>
      <Forenames>A. C</Forenames>
      <PageNumber>13796</PageNumber>
    </MainItem>
  </ItemGroup>
  <ItemGroup>
    <MainItem>
      <Key>
        <KeyDitto>___ ___ ___</KeyDitto>
      </Key>
      <Forenames>C. A</Forenames>
      <PageNumber>12119</PageNumber>
    </MainItem>
  </ItemGroup>
  <ItemGroup>
    <MainItem>
      <Key>
        <KeyDitto>___ ___ ___</KeyDitto>
      </Key>
      <Forenames>H. M.</Forenames>
      <PageNumber>13799</PageNumber>
    </MainItem>
  </ItemGroup>
  <ItemGroup>
    <MainItem>
      <Key>
        <KeyDitto>___ ___</KeyDitto>
      </Key>
      <Forenames>J. A</Forenames>
      <PageNumber>12668</PageNumber>
    </MainItem>
  </ItemGroup>
  <ItemGroup>
    <MainItem>
      <Key>
        <KeyDitto>___ ___</KeyDitto>
      </Key>
      <Forenames>J. G</Forenames>
      <PageNumber>11321</PageNumber>
    </MainItem>
  </ItemGroup>
  <ItemGroup>
    <MainItem>
      <Key>
        <KeyDitto>___ ___</KeyDitto>
      </Key>
      <Forenames>J. M. P.</Forenames>
      <PageNumber>13916</PageNumber>
    </MainItem>
  </ItemGroup>
  <ItemGroup>
    <MainItem>
      <Key>
        <KeyDitto>___ ___</KeyDitto>
      </Key>
      <Forenames>J. N. G.</Forenames>
      <PageNumber>11846</PageNumber>
    </MainItem>
  </ItemGroup>
  <ItemGroup>
    <MainItem>
      <Key>
        <KeyDitto>___ ___</KeyDitto>
      </Key>
      <Forenames>J. S. W.</Forenames>
      <PageNumber>11329</PageNumber>
    </MainItem>
  </ItemGroup>
  <ItemGroup>
    <MainItem>
      <Key>
        <KeyDitto>___ ___ ___</KeyDitto>
      </Key>
      <Forenames>M. G</Forenames>
      <PageNumber>13509</PageNumber>
    </MainItem>
  </ItemGroup>
  <ItemGroup>
    <MainItem>
      <Key>
        <KeyDitto>___ ___ ___</KeyDitto>
      </Key>
      <Forenames>P. D</Forenames>
      <PageNumber>13915</PageNumber>
    </MainItem>
  </ItemGroup>
  <ItemGroup>
    <MainItem>
      <Key>
        <KeyDitto>___ ___</KeyDitto>
      </Key>
      <Forenames>S</Forenames>
      <PageNumber>12668</PageNumber>
    </MainItem>
  </ItemGroup>
  <ItemGroup>
    <MainItem>
      <Key>
        <KeyDitto>___ ___</KeyDitto>
      </Key>
      <Forenames>T</Forenames>
      <PageNumber>12671</PageNumber>
    </MainItem>
  </ItemGroup>
  <ItemGroup>
    <MainItem>
      <Key>Scott-Barrett</Key>
      <Forenames>J.</Forenames>
      <PageNumber>11581</PageNumber>
    </MainItem>
  </ItemGroup>
  <ItemGroup>
    <MainItem>
      <Key>Scott-Clarke</Key>
      <Forenames>J. S.</Forenames>
      <PageNumber>11326</PageNumber>
    </MainItem>
  </ItemGroup>
  <ItemGroup>
    <MainItem>
      <Key>Scragg</Key>
      <Forenames>S. M.</Forenames>
      <PageNumber>11848</PageNumber>
    </MainItem>
  </ItemGroup>
  <ItemGroup>
    <MainItem>
      <Key>Screen</Key>
      <Forenames>R. H.</Forenames>
      <PageNumber>12406</PageNumber>
    </MainItem>
  </ItemGroup>
  <ItemGroup>
    <MainItem>
      <Key>Scrimgeour</Key>
      <Forenames>J.</Forenames>
      <PageNumber>10777</PageNumber>
    </MainItem>
  </ItemGroup>
  <ItemGroup>
    <MainItem>
      <Key>Scrivener</Key>
      <Forenames>A. T.</Forenames>
      <PageNumber>13913</PageNumber>
    </MainItem>
  </ItemGroup>
  <ItemGroup>
    <MainItem>
      <Key>
        <KeyDitto>___ ___</KeyDitto>
      </Key>
      <Forenames>D. J</Forenames>
      <PageNumber>10773</PageNumber>
    </MainItem>
  </ItemGroup>
  <ItemGroup>
    <MainItem>
      <Key>Scrope</Key>
      <Forenames>P. A.</Forenames>
      <PageNumber>12403</PageNumber>
    </MainItem>
  </ItemGroup>
  <ItemGroup>
    <MainItem>
      <Key>Scruby</Key>
      <Forenames>D.</Forenames>
      <Text>MacE</Text>
      <PageNumber>12401</PageNumber>
    </MainItem>
  </ItemGroup>
  <ItemGroup>
    <MainItem>
      <Key>Seabrook</Key>
      <Forenames>P. W. G.</Forenames>
      <PageNumber>13910</PageNumber>
    </MainItem>
  </ItemGroup>
  <ItemGroup>
    <MainItem>
      <Key>Seaby</Key>
      <Forenames>E. W.</Forenames>
      <PageNumber>10776</PageNumber>
    </MainItem>
  </ItemGroup>
  <ItemGroup>
    <MainItem>
      <Key>Seager</Key>
      <Forenames>W. J. B.</Forenames>
      <PageNumber>13228</PageNumber>
    </MainItem>
  </ItemGroup>
  <ItemGroup>
    <MainItem>
      <Key>Searle</Key>
      <Forenames>F. T.</Forenames>
      <PageNumber>12666</PageNumber>
    </MainItem>
  </ItemGroup>
  <ItemGroup>
    <MainItem>
      <Key>
        <KeyDitto>___ ___ ___</KeyDitto>
      </Key>
      <Forenames>P. J</Forenames>
      <PageNumber>13909</PageNumber>
    </MainItem>
  </ItemGroup>
  <ItemGroup>
    <MainItem>
      <Key>Seaton</Key>
      <Forenames>D. J.</Forenames>
      <PageNumber>10534</PageNumber>
    </MainItem>
  </ItemGroup>
  <ItemGroup>
    <MainItem>
      <Key>Sechiari</Key>
      <Forenames>G.</Forenames>
      <PageNumber>12667</PageNumber>
    </MainItem>
  </ItemGroup>
  <ItemGroup>
    <MainItem>
      <Key>Seddon</Key>
      <Forenames>R</Forenames>
      <PageNumber>10532</PageNumber>
    </MainItem>
  </ItemGroup>
  <ItemGroup>
    <MainItem>
      <Key>Sedgbeer</Key>
      <Forenames>I. J.</Forenames>
      <PageNumber>13908</PageNumber>
    </MainItem>
  </ItemGroup>
  <ItemGroup>
    <MainItem>
      <Key>Seear</Key>
      <Forenames>M. H.</Forenames>
      <PageNumber>11327</PageNumber>
    </MainItem>
  </ItemGroup>
  <ItemGroup>
    <MainItem>
      <Key>Seed</Key>
      <Forenames>D</Forenames>
      <PageNumber>11327</PageNumber>
    </MainItem>
  </ItemGroup>
  <ItemGroup>
    <MainItem>
      <Key>Seekings</Key>
      <Forenames>P. C.</Forenames>
      <PageNumber>12943</PageNumber>
    </MainItem>
  </ItemGroup>
  <ItemGroup>
    <MainItem>
      <Key>Seel</Key>
      <Forenames>J. R</Forenames>
      <PageNumber>12401</PageNumber>
    </MainItem>
  </ItemGroup>
  <ItemGroup>
    <MainItem>
      <Key>Seidelin</Key>
      <Forenames>R.</Forenames>
      <PageNumber>13799</PageNumber>
    </MainItem>
  </ItemGroup>
  <ItemGroup>
    <MainItem>
      <Key>Selby-Boothroyd</Key>
      <Forenames>R. G.</Forenames>
      <PageNumber>13227</PageNumber>
    </MainItem>
  </ItemGroup>
  <ItemGroup>
    <MainItem>
      <Key>Sellars</Key>
      <Forenames>N. A.</Forenames>
      <PageNumber>10776</PageNumber>
    </MainItem>
  </ItemGroup>
  <ItemGroup>
    <MainItem>
      <Key>Sellick</Key>
      <Forenames>F. J.</Forenames>
      <PageNumber>12946</PageNumber>
    </MainItem>
  </ItemGroup>
  <ItemGroup>
    <MainItem>
      <Key>Semple</Key>
      <Forenames>J. W.</Forenames>
      <PageNumber>12119</PageNumber>
    </MainItem>
  </ItemGroup>
  <ItemGroup>
    <MainItem>
      <Key>Senior</Key>
      <Forenames>G. K.</Forenames>
      <PageNumber>11053</PageNumber>
      <PageNumber>12122</PageNumber>
    </MainItem>
  </ItemGroup>
  <ItemGroup>
    <MainItem>
      <Key>Serle</Key>
      <Forenames>J. P. D.</Forenames>
      <PageNumber>12666</PageNumber>
    </MainItem>
  </ItemGroup>
  <ItemGroup>
    <MainItem>
      <Key>Sert</Key>
      <Text>&gt;ell, B. W</Text>
      <PageNumber>12120</PageNumber>
    </MainItem>
  </ItemGroup>
  <ItemGroup>
    <MainItem>
      <Key>Setford</Key>
      <Forenames>J. D.</Forenames>
      <PageNumber>11840</PageNumber>
    </MainItem>
  </ItemGroup>
  <ItemGroup>
    <MainItem>
      <Key>Settle</Key>
      <Forenames>J. A.</Forenames>
      <PageNumber>10771</PageNumber>
    </MainItem>
  </ItemGroup>
  <ItemGroup>
    <MainItem>
      <Key>Sewell</Key>
      <Forenames>D. E.</Forenames>
      <PageNumber>11322</PageNumber>
    </MainItem>
  </ItemGroup>
  <ItemGroup>
    <MainItem>
      <Key>Sex</Key>
      <Forenames>T. J. F.</Forenames>
      <PageNumber>13907</PageNumber>
    </MainItem>
  </ItemGroup>
  <ItemGroup>
    <MainItem>
      <Key>Sexton</Key>
      <Forenames>M. E.</Forenames>
      <PageNumber>12666</PageNumber>
    </MainItem>
  </ItemGroup>
  <ItemGroup>
    <MainItem>
      <Key>Seymour</Key>
      <Forenames>J.</Forenames>
      <PageNumber>11843</PageNumber>
    </MainItem>
  </ItemGroup>
  <ItemGroup>
    <MainItem>
      <Key>Shales</Key>
      <Forenames>R. A.</Forenames>
      <PageNumber>13510</PageNumber>
    </MainItem>
  </ItemGroup>
  <ItemGroup>
    <MainItem>
      <Key>Shambrook</Key>
      <Forenames>D.</Forenames>
      <PageNumber>12120</PageNumber>
    </MainItem>
  </ItemGroup>
  <ItemGroup>
    <MainItem>
      <Key>Shanks</Key>
      <Forenames>C. R.</Forenames>
      <PageNumber>11587</PageNumber>
    </MainItem>
  </ItemGroup>
  <ItemGroup>
    <MainItem>
      <Key>Shapland</Key>
      <Forenames>P. C.</Forenames>
      <PageNumber>13910</PageNumber>
    </MainItem>
  </ItemGroup>
  <ItemGroup>
    <MainItem>
      <Key>
        <KeyDitto>___ ___</KeyDitto>
      </Key>
      <Forenames>R. A.</Forenames>
      <PageNumber>13915</PageNumber>
    </MainItem>
  </ItemGroup>
  <ItemGroup>
    <MainItem>
      <Key>Sharman</Key>
      <Forenames>M. F</Forenames>
      <PageNumber>10533</PageNumber>
    </MainItem>
  </ItemGroup>
  <ItemGroup>
    <MainItem>
      <Key>Sharp</Key>
      <Forenames>A. L.</Forenames>
      <PageNumber>11846</PageNumber>
    </MainItem>
  </ItemGroup>
  <ItemGroup>
    <MainItem>
      <Key>
        <KeyDitto>___ ___</KeyDitto>
      </Key>
      <Forenames>D. A.</Forenames>
      <PageNumber>13795</PageNumber>
    </MainItem>
  </ItemGroup>
  <ItemGroup>
    <MainItem>
      <Key>
        <KeyDitto>___ ___</KeyDitto>
      </Key>
      <Forenames>E. K. J.</Forenames>
      <PageNumber>12945</PageNumber>
    </MainItem>
  </ItemGroup>
  <ItemGroup>
    <MainItem>
      <Key>
        <KeyDitto>___ ___</KeyDitto>
      </Key>
      <Forenames>F. M.</Forenames>
      <PageNumber>11847</PageNumber>
    </MainItem>
  </ItemGroup>
  <ItemGroup>
    <MainItem>
      <Key>Sharp</Key>
      <Forenames>I. F</Forenames>
      <PageNumber>13511</PageNumber>
    </MainItem>
  </ItemGroup>
  <ItemGroup>
    <MainItem>
      <Key>
        <KeyDitto>___ ___</KeyDitto>
      </Key>
      <Forenames>K. G</Forenames>
      <PageNumber>13917</PageNumber>
    </MainItem>
  </ItemGroup>
  <ItemGroup>
    <MainItem>
      <Key>
        <KeyDitto>___ ___ ___</KeyDitto>
      </Key>
      <Forenames>O. B</Forenames>
      <PageNumber>11839</PageNumber>
    </MainItem>
  </ItemGroup>
  <ItemGroup>
    <MainItem>
      <Key>Sharpe</Key>
      <Forenames>G. D.</Forenames>
      <PageNumber>13908</PageNumber>
    </MainItem>
  </ItemGroup>
  <ItemGroup>
    <MainItem>
      <Key>
        <KeyDitto>___ ___ ___</KeyDitto>
      </Key>
      <Forenames>J. P</Forenames>
      <PageNumber>11848</PageNumber>
    </MainItem>
  </ItemGroup>
  <ItemGroup>
    <MainItem>
      <Key>
        <KeyDitto>___ ___ ___</KeyDitto>
      </Key>
      <Forenames>M. H</Forenames>
      <PageNumber>13227</PageNumber>
    </MainItem>
  </ItemGroup>
  <ItemGroup>
    <MainItem>
      <Key>Shattock</Key>
      <Forenames>W. R. W.</Forenames>
      <PageNumber>11330</PageNumber>
    </MainItem>
  </ItemGroup>
  <ItemGroup>
    <MainItem>
      <Key>Shaw</Key>
      <Forenames>B. W. B.</Forenames>
      <PageNumber>12670</PageNumber>
    </MainItem>
  </ItemGroup>
  <ItemGroup>
    <MainItem>
      <Key>
        <KeyDitto>___ ___ ___</KeyDitto>
      </Key>
      <Forenames>C. G</Forenames>
      <PageNumber>13230</PageNumber>
    </MainItem>
  </ItemGroup>
  <ItemGroup>
    <MainItem>
      <Key>
        <KeyDitto>___ ___ ___</KeyDitto>
      </Key>
      <Forenames>D</Forenames>
      <PageNumber>13912</PageNumber>
    </MainItem>
  </ItemGroup>
  <ItemGroup>
    <MainItem>
      <Key>
        <KeyDitto>___ ___ ___</KeyDitto>
      </Key>
      <Forenames>D. C</Forenames>
      <PageNumber>10534</PageNumber>
    </MainItem>
  </ItemGroup>
  <ItemGroup>
    <MainItem>
      <Key>
        <KeyDitto>___ ___ ___</KeyDitto>
      </Key>
      <Forenames>D. S</Forenames>
      <PageNumber>11328</PageNumber>
    </MainItem>
  </ItemGroup>
  <ItemGroup>
    <MainItem>
      <Key>
        <KeyDitto>___ ___ ___</KeyDitto>
      </Key>
      <Forenames>F. M</Forenames>
      <PageNumber>13509</PageNumber>
    </MainItem>
  </ItemGroup>
  <ItemGroup>
    <MainItem>
      <Key>
        <KeyDitto>___ ___ ___</KeyDitto>
      </Key>
      <Forenames>J.</Forenames>
      <Text>McC. M</Text>
      <PageNumber>12119</PageNumber>
    </MainItem>
  </ItemGroup>
  <ItemGroup>
    <MainItem>
      <Key>
        <KeyDitto>___ ___ ___</KeyDitto>
      </Key>
      <Forenames>P. J</Forenames>
      <PageNumber>11839</PageNumber>
    </MainItem>
  </ItemGroup>
  <ItemGroup>
    <MainItem>
      <Key>Shaw-Brown</Key>
      <Forenames>K. M.</Forenames>
      <PageNumber>10777</PageNumber>
    </MainItem>
  </ItemGroup>
  <ItemGroup>
    <MainItem>
      <Key>
        <KeyDitto>___ ___</KeyDitto>
      </Key>
      <Forenames>R. D.</Forenames>
      <PageNumber>11326</PageNumber>
    </MainItem>
  </ItemGroup>
  <ItemGroup>
    <MainItem>
      <Key>Shea-Simonds</Key>
      <Forenames>G. C.</Forenames>
      <PageNumber>13795</PageNumber>
    </MainItem>
  </ItemGroup>
  <ItemGroup>
    <MainItem>
      <Key>Shead</Key>
      <Forenames>S. N.</Forenames>
      <PageNumber>12404</PageNumber>
    </MainItem>
  </ItemGroup>
  <ItemGroup>
    <MainItem>
      <Key>Shearer</Key>
      <Forenames>P. J.</Forenames>
      <PageNumber>12121</PageNumber>
    </MainItem>
  </ItemGroup>
  <ItemGroup>
    <MainItem>
      <Key>Shears</Key>
      <Forenames>A. J.</Forenames>
      <PageNumber>11841</PageNumber>
    </MainItem>
  </ItemGroup>
  <ItemGroup>
    <MainItem>
      <Key>Sheddick</Key>
      <Forenames>J. P. A.</Forenames>
      <PageNumber>13226</PageNumber>
    </MainItem>
  </ItemGroup>
  <ItemGroup>
    <MainItem>
      <Key>Sheen</Key>
      <Forenames>T. A.</Forenames>
      <PageNumber>10534</PageNumber>
    </MainItem>
  </ItemGroup>
  <ItemGroup>
    <MainItem>
      <Key>Sheffield-Parker</Key>
      <Forenames>M. J.</Forenames>
      <PageNumber>12668</PageNumber>
    </MainItem>
  </ItemGroup>
  <ItemGroup>
    <MainItem>
      <Key>Shekbahadur</Key>
      <Forenames>Gurung</Forenames>
      <PageNumber>11843</PageNumber>
    </MainItem>
  </ItemGroup>
  <ItemGroup>
    <MainItem>
      <Key>Shellswell</Key>
      <Forenames>M. A.</Forenames>
      <PageNumber>13794</PageNumber>
    </MainItem>
  </ItemGroup>
  <ItemGroup>
    <MainItem>
      <Key>Shennan</Key>
      <Forenames>M. K</Forenames>
      <PageNumber>13911</PageNumber>
    </MainItem>
  </ItemGroup>
  <ItemGroup>
    <MainItem>
      <Key>Shepherd</Key>
      <Forenames>S. G.</Forenames>
      <PageNumber>11586</PageNumber>
    </MainItem>
  </ItemGroup>
  <ItemGroup>
    <MainItem>
      <Key>Shepley</Key>
      <Forenames>R. M.</Forenames>
      <PageNumber>10772</PageNumber>
    </MainItem>
  </ItemGroup>
  <ItemGroup>
    <MainItem>
      <Key>Sheppard</Key>
      <Forenames>B.</Forenames>
      <PageNumber>12121</PageNumber>
    </MainItem>
  </ItemGroup>
  <ItemGroup>
    <MainItem>
      <Key>
        <KeyDitto>___ ___</KeyDitto>
      </Key>
      <Forenames>D. A.</Forenames>
      <Text>j:</Text>
      <PageNumber>11321</PageNumber>
    </MainItem>
  </ItemGroup>
  <ItemGroup>
    <MainItem>
      <Key>
        <KeyDitto>___ ___ .</KeyDitto>
      </Key>
      <Forenames>P. J.</Forenames>
      <PageNumber>10773</PageNumber>
    </MainItem>
  </ItemGroup>
  <ItemGroup>
    <MainItem>
      <Key>Shepperd</Key>
      <Forenames>K. H.</Forenames>
      <PageNumber>11588</PageNumber>
    </MainItem>
  </ItemGroup>
  <ItemGroup>
    <MainItem>
      <Key>Shepperson</Key>
      <Forenames>D. A.</Forenames>
      <PageNumber>12670</PageNumber>
    </MainItem>
  </ItemGroup>
  <ItemGroup>
    <MainItem>
      <Key>Sheran</Key>
      <Forenames>J. D.</Forenames>
      <PageNumber>11845</PageNumber>
    </MainItem>
  </ItemGroup>
  <ItemGroup>
    <MainItem>
      <Key>Shere</Key>
      <Forenames>G. J</Forenames>
      <PageNumber>11847</PageNumber>
    </MainItem>
  </ItemGroup>
  <ItemGroup>
    <MainItem>
      <Key>Sheridan</Key>
      <Forenames>K. P.</Forenames>
      <PageNumber>11587</PageNumber>
    </MainItem>
  </ItemGroup>
  <ItemGroup>
    <MainItem>
      <Key>
        <KeyDitto>___ ___ ___</KeyDitto>
      </Key>
      <Forenames>P. J</Forenames>
      <PageNumber>13915</PageNumber>
    </MainItem>
  </ItemGroup>
  <ItemGroup>
    <MainItem>
      <Key>Sherrington</Key>
      <Forenames>T. B.</Forenames>
      <PageNumber>11329</PageNumber>
    </MainItem>
  </ItemGroup>
  <ItemGroup>
    <MainItem>
      <Key>Sherwin</Key>
      <Forenames>C. P.</Forenames>
      <PageNumber>11321</PageNumber>
    </MainItem>
  </ItemGroup>
  <ItemGroup>
    <MainItem>
      <Key>Shibu</Key>
      <Title>Gurung .</Title>
      <PageNumber>12404</PageNumber>
    </MainItem>
  </ItemGroup>
  <ItemGroup>
    <MainItem>
      <Key>Shields</Key>
      <Forenames>G.</Forenames>
      <PageNumber>10771</PageNumber>
    </MainItem>
  </ItemGroup>
  <ItemGroup>
    <MainItem>
      <Key>ShElito</Key>
      <Forenames>L. A.</Forenames>
      <PageNumber>11847</PageNumber>
    </MainItem>
  </ItemGroup>
  <ItemGroup>
    <MainItem>
      <Key>Shine</Key>
      <Forenames>J. K. W.</Forenames>
      <PageNumber>12122</PageNumber>
    </MainItem>
  </ItemGroup>
  <ItemGroup>
    <MainItem>
      <Key>Shivcharan</Key>
      <Forenames>Gurung</Forenames>
      <PageNumber>11050</PageNumber>
    </MainItem>
  </ItemGroup>
  <ItemGroup>
    <MainItem>
      <Key>Shoolbred</Key>
      <Forenames>R. G.</Forenames>
      <PageNumber>11582</PageNumber>
    </MainItem>
  </ItemGroup>
  <ItemGroup>
    <MainItem>
      <Key>Short</Key>
      <Forenames>A. F.</Forenames>
      <PageNumber>11329</PageNumber>
    </MainItem>
  </ItemGroup>
  <ItemGroup>
    <MainItem>
      <Key>
        <KeyDitto>___ ___</KeyDitto>
      </Key>
      <Text>CD</Text>
      <PageNumber>11846</PageNumber>
    </MainItem>
  </ItemGroup>
  <ItemGroup>
    <MainItem>
      <Key>
        <KeyDitto>___ ___ ___</KeyDitto>
      </Key>
      <Forenames>L. W. R.</Forenames>
      <PageNumber>12944</PageNumber>
    </MainItem>
  </ItemGroup>
  <ItemGroup>
    <MainItem>
      <Key>
        <KeyDitto>___ ___</KeyDitto>
      </Key>
      <Forenames>W.R</Forenames>
      <PageNumber>10531</PageNumber>
    </MainItem>
  </ItemGroup>
  <ItemGroup>
    <MainItem>
      <Key>Shreeve</Key>
      <Forenames>C. J.</Forenames>
      <PageNumber>13231</PageNumber>
    </MainItem>
  </ItemGroup>
  <ItemGroup>
    <MainItem>
      <Key>Shrives</Key>
      <Forenames>J. M.</Forenames>
      <PageNumber>13907</PageNumber>
    </MainItem>
  </ItemGroup>
  <ItemGroup>
    <MainItem>
      <Key>Shuldham</Key>
      <Forenames>R. A. Q.</Forenames>
      <PageNumber>11842</PageNumber>
    </MainItem>
  </ItemGroup>
  <ItemGroup>
    <MainItem>
      <Key>Shute</Key>
      <Forenames>D. H. C.</Forenames>
      <PageNumber>11845</PageNumber>
    </MainItem>
  </ItemGroup>
  <ItemGroup>
    <MainItem>
      <Key>Shuttleworth</Key>
      <Forenames>H. M.</Forenames>
      <PageNumber>11844</PageNumber>
    </MainItem>
  </ItemGroup>
  <ItemGroup>
    <MainItem>
      <Key>Sibbald</Key>
      <Forenames>P. F. A.</Forenames>
      <PageNumber>13911</PageNumber>
    </MainItem>
  </ItemGroup>
  <ItemGroup>
    <MainItem>
      <Key>Sidey</Key>
      <Forenames>E. S.</Forenames>
      <PageNumber>12945</PageNumber>
      <PageNumber>13230</PageNumber>
    </MainItem>
  </ItemGroup>
  <ItemGroup>
    <MainItem>
      <Key>Sievers</Key>
      <Forenames>J. D.</Forenames>
      <PageNumber>11839</PageNumber>
    </MainItem>
  </ItemGroup>
  <ItemGroup>
    <MainItem>
      <Key>Silk</Key>
      <Forenames>D. J</Forenames>
      <PageNumber>11054</PageNumber>
    </MainItem>
  </ItemGroup>
  <ItemGroup>
    <MainItem>
      <Key>
        <KeyDitto>___ ___</KeyDitto>
      </Key>
      <Forenames>R. G</Forenames>
      <PageNumber>13795</PageNumber>
    </MainItem>
  </ItemGroup>
  <ItemGroup>
    <MainItem>
      <Key>Sillett</Key>
      <Forenames>S. W.</Forenames>
      <PageNumber>10773</PageNumber>
    </MainItem>
  </ItemGroup>
  <ItemGroup>
    <MainItem>
      <Key>Sals</Key>
      <Forenames>J. A</Forenames>
      <PageNumber>11848</PageNumber>
    </MainItem>
  </ItemGroup>
  <ItemGroup>
    <MainItem>
      <Key>Silverman</Key>
      <Forenames>P. G.</Forenames>
      <PageNumber>11582</PageNumber>
    </MainItem>
  </ItemGroup>
  <ItemGroup>
    <MainItem>
      <Key>
        <KeyDitto>___ ___ ___</KeyDitto>
      </Key>
      <Forenames>S. G</Forenames>
      <PageNumber>13799</PageNumber>
    </MainItem>
  </ItemGroup>
  <ItemGroup>
    <MainItem>
      <Key>Silvey</Key>
      <Forenames>G. H.</Forenames>
      <PageNumber>13796</PageNumber>
    </MainItem>
  </ItemGroup>
  <ItemGroup>
    <MainItem>
      <Key>
        <KeyDitto>___ ___ ___</KeyDitto>
      </Key>
      <Forenames>P. B</Forenames>
      <PageNumber>12941</PageNumber>
    </MainItem>
  </ItemGroup>
  <ItemGroup>
    <MainItem>
      <Key>Sim</Key>
      <Forenames>G. F.</Forenames>
      <PageNumber>11849</PageNumber>
    </MainItem>
  </ItemGroup>
  <ItemGroup>
    <MainItem>
      <Key>
        <KeyDitto>___ ___</KeyDitto>
      </Key>
      <Forenames>J. A. N.</Forenames>
      <PageNumber>13227</PageNumber>
    </MainItem>
  </ItemGroup>
  <ItemGroup>
    <MainItem>
      <Key>Siminson</Key>
      <Forenames>A. H.</Forenames>
      <PageNumber>11053</PageNumber>
    </MainItem>
  </ItemGroup>
  <ItemGroup>
    <MainItem>
      <Key>Simm</Key>
      <Forenames>A. P.</Forenames>
      <PageNumber>13795</PageNumber>
    </MainItem>
  </ItemGroup>
  <ItemGroup>
    <MainItem>
      <Key>Simmonds</Key>
      <Forenames>P.</Forenames>
      <PageNumber>12667</PageNumber>
    </MainItem>
  </ItemGroup>
  <ItemGroup>
    <MainItem>
      <Key>Simmons</Key>
      <Forenames>A. E.</Forenames>
      <PageNumber>13912</PageNumber>
    </MainItem>
  </ItemGroup>
  <ItemGroup>
    <MainItem>
      <Key>
        <KeyDitto>___ ___ ___</KeyDitto>
      </Key>
      <Forenames>R. F. W.</Forenames>
      <PageNumber>13912</PageNumber>
    </MainItem>
  </ItemGroup>
  <ItemGroup>
    <MainItem>
      <Key>
        <KeyDitto>___ ___</KeyDitto>
      </Key>
      <Forenames>W. J</Forenames>
      <PageNumber>11583</PageNumber>
    </MainItem>
  </ItemGroup>
  <ItemGroup>
    <MainItem>
      <Key>Simms</Key>
      <Forenames>A. B.</Forenames>
      <PageNumber>13913</PageNumber>
    </MainItem>
  </ItemGroup>
  <ItemGroup>
    <MainItem>
      <Key>
        <KeyDitto>___ ___ ___</KeyDitto>
      </Key>
      <Forenames>R. M</Forenames>
      <PageNumber>10534</PageNumber>
    </MainItem>
  </ItemGroup>
  <ItemGroup>
    <MainItem>
      <Key>Simpkin</Key>
      <Forenames>R. A.</Forenames>
      <PageNumber>12407</PageNumber>
    </MainItem>
  </ItemGroup>
  <ItemGroup>
    <MainItem>
      <Key>Simpson</Key>
      <Forenames>A. D.</Forenames>
      <PageNumber>11329</PageNumber>
    </MainItem>
  </ItemGroup>
  <ItemGroup>
    <MainItem>
      <Key>
        <KeyDitto>___ ___ ___</KeyDitto>
      </Key>
      <Forenames>A. T. B. C.</Forenames>
      <PageNumber>13907</PageNumber>
    </MainItem>
  </ItemGroup>
  <ItemGroup>
    <MainItem>
      <Key>
        <KeyDitto>___ ___ ___ ___</KeyDitto>
      </Key>
      <Forenames>C. A</Forenames>
      <PageNumber>11583</PageNumber>
    </MainItem>
  </ItemGroup>
  <ItemGroup>
    <MainItem>
      <Key>
        <KeyDitto>___ ___</KeyDitto>
      </Key>
      <Forenames>G. L</Forenames>
      <PageNumber>13226</PageNumber>
    </MainItem>
  </ItemGroup>
  <ItemGroup>
    <MainItem>
      <Key>
        <KeyDitto>___ ___ ___</KeyDitto>
      </Key>
      <Forenames>G. M. C.</Forenames>
      <PageNumber>12407</PageNumber>
    </MainItem>
  </ItemGroup>
  <ItemGroup>
    <MainItem>
      <Key>
        <KeyDitto>___ ___</KeyDitto>
      </Key>
      <Forenames>J. R</Forenames>
      <PageNumber>13227</PageNumber>
    </MainItem>
  </ItemGroup>
  <ItemGroup>
    <MainItem>
      <Key>
        <KeyDitto>___ ___ ___</KeyDitto>
      </Key>
      <Forenames>L. N</Forenames>
      <PageNumber>12944</PageNumber>
    </MainItem>
  </ItemGroup>
  <ItemGroup>
    <MainItem>
      <Key>
        <KeyDitto>___ ___ ___ ___</KeyDitto>
      </Key>
      <Forenames>R. T</Forenames>
      <PageNumber>13232</PageNumber>
    </MainItem>
  </ItemGroup>
  <ItemGroup>
    <MainItem>
      <Key>
        <KeyDitto>___ ___</KeyDitto>
      </Key>
      <Forenames>W. D</Forenames>
      <PageNumber>13798</PageNumber>
    </MainItem>
  </ItemGroup>
  <ItemGroup>
    <MainItem>
      <Key>Simpson-Gee</Key>
      <Forenames>C. J.</Forenames>
      <PageNumber>11841</PageNumber>
    </MainItem>
  </ItemGroup>
  <ItemGroup>
    <MainItem>
      <Key>Sims</Key>
      <Forenames>M. C.</Forenames>
      <PageNumber>11327</PageNumber>
    </MainItem>
  </ItemGroup>
  <ItemGroup>
    <MainItem>
      <Key>
        <KeyDitto>___ ___ ___</KeyDitto>
      </Key>
      <Forenames>T. H</Forenames>
      <PageNumber>11588</PageNumber>
    </MainItem>
  </ItemGroup>
  <ItemGroup>
    <MainItem>
      <Key>Sinclair</Key>
      <Forenames>E. S.</Forenames>
      <PageNumber>11052</PageNumber>
    </MainItem>
  </ItemGroup>
  <ItemGroup>
    <MainItem>
      <Key>
        <KeyDitto>___ ___ ___</KeyDitto>
      </Key>
      <Forenames>P. A.</Forenames>
      <PageNumber>10535</PageNumber>
    </MainItem>
  </ItemGroup>
  <ItemGroup>
    <MainItem>
      <Key>Sincock</Key>
      <Forenames>P. J.</Forenames>
      <PageNumber>13911</PageNumber>
    </MainItem>
  </ItemGroup>
  <ItemGroup>
    <MainItem>
      <Key>Singleton</Key>
      <Forenames>J. E.</Forenames>
      <PageNumber>13515</PageNumber>
    </MainItem>
  </ItemGroup>
  <ItemGroup>
    <MainItem>
      <Key>Sjoberg</Key>
      <Forenames>R.</Forenames>
      <PageNumber>13793</PageNumber>
    </MainItem>
  </ItemGroup>
  <ItemGroup>
    <MainItem>
      <Key>Skaife</Key>
      <Forenames>R. J.</Forenames>
      <PageNumber>11326</PageNumber>
    </MainItem>
  </ItemGroup>
  <ItemGroup>
    <MainItem>
      <Key>Skailes</Key>
      <Forenames>D. S. D</Forenames>
      <PageNumber>11581</PageNumber>
    </MainItem>
  </ItemGroup>
  <ItemGroup>
    <MainItem>
      <Key>Skilton</Key>
      <Forenames>C. H.</Forenames>
      <PageNumber>12944</PageNumber>
    </MainItem>
  </ItemGroup>
  <ItemGroup>
    <MainItem>
      <Key>Skinner</Key>
      <Forenames>A. P.</Forenames>
      <PageNumber>13914</PageNumber>
    </MainItem>
  </ItemGroup>
  <ItemGroup>
    <MainItem>
      <Key>
        <KeyDitto>___ ___ ___</KeyDitto>
      </Key>
      <Forenames>D. R.</Forenames>
      <PageNumber>13797</PageNumber>
    </MainItem>
  </ItemGroup>
  <ItemGroup>
    <MainItem>
      <Key>
        <KeyDitto>___ ___ ___</KeyDitto>
      </Key>
      <Forenames>D. W.</Forenames>
      <PageNumber>11321</PageNumber>
    </MainItem>
  </ItemGroup>
  <ItemGroup>
    <MainItem>
      <Key>
        <KeyDitto>___ ___ ___</KeyDitto>
      </Key>
      <Forenames>R. S.</Forenames>
      <PageNumber>11322</PageNumber>
    </MainItem>
  </ItemGroup>
  <ItemGroup>
    <MainItem>
      <Key>Skone</Key>
      <Forenames>J. F.</Forenames>
      <PageNumber>12944</PageNumber>
    </MainItem>
  </ItemGroup>
  <ItemGroup>
    <MainItem>
      <Key>Sladden</Key>
      <Forenames>R. E. A.</Forenames>
      <PageNumber>11328</PageNumber>
    </MainItem>
  </ItemGroup>
  <ItemGroup>
    <MainItem>
      <Key>Slade</Key>
      <Forenames>C. J. B.</Forenames>
      <PageNumber>13913</PageNumber>
    </MainItem>
  </ItemGroup>
  <ItemGroup>
    <MainItem>
      <Key>
        <KeyDitto>___ ___</KeyDitto>
      </Key>
      <Forenames>J.</Forenames>
      <PageNumber>11327</PageNumber>
    </MainItem>
  </ItemGroup>
  <ItemGroup>
    <MainItem>
      <Key>Slater</Key>
      <Forenames>A. D.</Forenames>
      <PageNumber>13916</PageNumber>
    </MainItem>
  </ItemGroup>
  <ItemGroup>
    <MainItem>
      <Key>
        <KeyDitto>___ ___ ___</KeyDitto>
      </Key>
      <Forenames>D. E.</Forenames>
      <PageNumber>13909</PageNumber>
    </MainItem>
  </ItemGroup>
  <ItemGroup>
    <MainItem>
      <Key>
        <KeyDitto>___ ___ ___</KeyDitto>
      </Key>
      <Forenames>G.</Forenames>
      <PageNumber>11321</PageNumber>
    </MainItem>
  </ItemGroup>
  <ItemGroup>
    <MainItem>
      <Key>
        <KeyDitto>___ ___ ___</KeyDitto>
      </Key>
      <Forenames>J. C. K.</Forenames>
      <PageNumber>12668</PageNumber>
    </MainItem>
  </ItemGroup>
  <ItemGroup>
    <MainItem>
      <Key>
        <KeyDitto>___ ___</KeyDitto>
      </Key>
      <Forenames>J. C. N.</Forenames>
      <PageNumber>13227</PageNumber>
    </MainItem>
  </ItemGroup>
  <ItemGroup>
    <MainItem>
      <Key>
        <KeyDitto>___ ___</KeyDitto>
      </Key>
      <Forenames>J. G.</Forenames>
      <PageNumber>11846</PageNumber>
    </MainItem>
  </ItemGroup>
  <ItemGroup>
    <MainItem>
      <Key>
        <KeyDitto>___ ___ ___</KeyDitto>
      </Key>
      <Forenames>G.</Forenames>
      <PageNumber>11847</PageNumber>
    </MainItem>
  </ItemGroup>
  <ItemGroup>
    <MainItem>
      <Key>Slatter</Key>
      <Forenames>S. O.</Forenames>
      <PageNumber>10536</PageNumber>
    </MainItem>
  </ItemGroup>
  <ItemGroup>
    <MainItem>
      <Key>Sleight</Key>
      <Forenames>J. H.</Forenames>
      <PageNumber>11054</PageNumber>
    </MainItem>
  </ItemGroup>
  <ItemGroup>
    <MainItem>
      <Key>Slinn</Key>
      <Forenames>G. K.</Forenames>
      <PageNumber>11050</PageNumber>
    </MainItem>
  </ItemGroup>
  <ItemGroup>
    <MainItem>
      <Key>Sloan</Key>
      <Forenames>C. E.</Forenames>
      <PageNumber>13914</PageNumber>
    </MainItem>
  </ItemGroup>
  <ItemGroup>
    <MainItem>
      <Key>
        <KeyDitto>___ ___ ___</KeyDitto>
      </Key>
      <Forenames>C. E. E.</Forenames>
      <PageNumber>13510</PageNumber>
    </MainItem>
  </ItemGroup>
  <ItemGroup>
    <MainItem>
      <Key>
        <KeyDitto>___ ___ ___</KeyDitto>
      </Key>
      <Forenames>G. E. E.</Forenames>
      <PageNumber>13912</PageNumber>
    </MainItem>
  </ItemGroup>
  <ItemGroup>
    <MainItem>
      <Key>
        <KeyDitto>___ ___</KeyDitto>
      </Key>
      <Forenames>H. M.</Forenames>
      <PageNumber>11325</PageNumber>
    </MainItem>
  </ItemGroup>
  <ItemGroup>
    <MainItem>
      <Key>Sloman</Key>
      <Forenames>M. J.</Forenames>
      <PageNumber>11328</PageNumber>
    </MainItem>
  </ItemGroup>
  <ItemGroup>
    <MainItem>
      <Key>Smaje</Key>
      <Forenames>C. P.</Forenames>
      <PageNumber>10776</PageNumber>
    </MainItem>
  </ItemGroup>
  <ItemGroup>
    <MainItem>
      <Key>Smale</Key>
      <Forenames>K. C.</Forenames>
      <PageNumber>11842</PageNumber>
    </MainItem>
  </ItemGroup>
  <ItemGroup>
    <MainItem>
      <Key>Smaller</Key>
      <Forenames>S. A.</Forenames>
      <PageNumber>12118</PageNumber>
    </MainItem>
  </ItemGroup>
  <ItemGroup>
    <MainItem>
      <Key>Smallridge</Key>
      <Forenames>K. J.</Forenames>
      <PageNumber>11326</PageNumber>
    </MainItem>
  </ItemGroup>
  <ItemGroup>
    <MainItem>
      <Key>Smart</Key>
      <Forenames>M. A. A.</Forenames>
      <PageNumber>11322</PageNumber>
      <PageNumber>11841</PageNumber>
    </MainItem>
  </ItemGroup>
  <ItemGroup>
    <MainItem>
      <Key>
        <KeyDitto>___ ___</KeyDitto>
      </Key>
      <Forenames>R. A .</Forenames>
      <PageNumber>11847</PageNumber>
    </MainItem>
  </ItemGroup>
  <ItemGroup>
    <MainItem>
      <Key>
        <KeyDitto>___ ___ ___</KeyDitto>
      </Key>
      <Forenames>S. A.</Forenames>
      <PageNumber>10531</PageNumber>
    </MainItem>
  </ItemGroup>
  <ItemGroup>
    <MainItem>
      <Key>Smeatham</Key>
      <Forenames>T. R.</Forenames>
      <PageNumber>13800</PageNumber>
    </MainItem>
  </ItemGroup>
  <ItemGroup>
    <MainItem>
      <Key>Smeed</Key>
      <Forenames>B. K.</Forenames>
      <PageNumber>11326</PageNumber>
    </MainItem>
  </ItemGroup>
  <ItemGroup>
    <MainItem>
      <Key>Smeeth</Key>
      <Forenames>P. M. A.</Forenames>
      <PageNumber>13228</PageNumber>
    </MainItem>
  </ItemGroup>
  <ItemGroup>
    <MainItem>
      <Key>Smeeton</Key>
      <Forenames>C. B. K.</Forenames>
      <PageNumber>11584</PageNumber>
    </MainItem>
  </ItemGroup>
  <ItemGroup>
    <MainItem>
      <Key>Smerdon</Key>
      <Forenames>A. W.</Forenames>
      <PageNumber>13510</PageNumber>
    </MainItem>
  </ItemGroup>
  <ItemGroup>
    <MainItem>
      <Key>Smith</Key>
      <Forenames>A</Forenames>
      <PageNumber>13232</PageNumber>
    </MainItem>
  </ItemGroup>
  <ItemGroup>
    <MainItem>
      <Key>
        <KeyDitto>___ ___ ___ ___</KeyDitto>
      </Key>
      <Forenames>A. C.</Forenames>
      <Text>(87958)</Text>
      <PageNumber>13511</PageNumber>
    </MainItem>
  </ItemGroup>
  <ItemGroup>
    <MainItem>
      <Key>
        <KeyDitto>___ ___ ___</KeyDitto>
      </Key>
      <Forenames>A. C.</Forenames>
      <Text>(486433)</Text>
      <PageNumber>11053</PageNumber>
      <PageNumber>12941</PageNumber>
    </MainItem>
  </ItemGroup>
  <ItemGroup>
    <MainItem>
      <Key>
        <KeyDitto>___ ___</KeyDitto>
      </Key>
      <Forenames>A. C. L.</Forenames>
      <PageNumber>12669</PageNumber>
    </MainItem>
  </ItemGroup>
  <ItemGroup>
    <MainItem>
      <Key>
        <KeyDitto>___ ___ ___</KeyDitto>
      </Key>
      <Forenames>A. N.</Forenames>
      <PageNumber>10772</PageNumber>
    </MainItem>
  </ItemGroup>
  <ItemGroup>
    <MainItem>
      <Key>
        <KeyDitto>___ ___</KeyDitto>
      </Key>
      <Forenames>B. J.</Forenames>
      <PageNumber>11052</PageNumber>
      <PageNumber>11325</PageNumber>
    </MainItem>
  </ItemGroup>
  <ItemGroup>
    <MainItem>
      <Key>
        <KeyDitto>___ ___ ___</KeyDitto>
      </Key>
      <Forenames>B. V. B.</Forenames>
      <PageNumber>11326</PageNumber>
    </MainItem>
  </ItemGroup>
  <ItemGroup>
    <MainItem>
      <Key>
        <KeyDitto>___ ___</KeyDitto>
      </Key>
      <Forenames>C</Forenames>
      <Text>J S</Text>
      <PageNumber>12403</PageNumber>
    </MainItem>
  </ItemGroup>
  <ItemGroup>
    <MainItem>
      <Key>
        <KeyDitto>___ ___ ___</KeyDitto>
      </Key>
      <Forenames>D.</Forenames>
      <Text>(291684)</Text>
      <PageNumber>13916</PageNumber>
    </MainItem>
  </ItemGroup>
  <KeyDitto>___ ___</KeyDitto>
  <ItemGroup>
    <MainItem>
      <Key>
        <KeyDitto>___ ___</KeyDitto>
      </Key>
      <Forenames>D. A.</Forenames>
      <Text>(2533386)</Text>
      <PageNumber>11328</PageNumber>
    </MainItem>
  </ItemGroup>
  <ItemGroup>
    <MainItem>
      <Key>
        <KeyDitto>___ ___ ___</KeyDitto>
      </Key>
      <Forenames>D. A.</Forenames>
      <Text>(4251591)</Text>
      <PageNumber>13513</PageNumber>
    </MainItem>
  </ItemGroup>
  <ItemGroup>
    <MainItem>
      <Key>
        <KeyDitto>___ ___</KeyDitto>
      </Key>
      <Forenames>D. C. M.</Forenames>
      <PageNumber>11587</PageNumber>
    </MainItem>
  </ItemGroup>
  <ItemGroup>
    <MainItem>
      <Key>
        <KeyDitto>___ ___ ___</KeyDitto>
      </Key>
      <Forenames>D. L</Forenames>
      <PageNumber>12119</PageNumber>
    </MainItem>
  </ItemGroup>
  <ItemGroup>
    <MainItem>
      <Key>
        <KeyDitto>___ ___</KeyDitto>
      </Key>
      <Forenames>D. T</Forenames>
      <PageNumber>11843</PageNumber>
    </MainItem>
  </ItemGroup>
  <ItemGroup>
    <MainItem>
      <Key>
        <KeyDitto>___ ___ ___</KeyDitto>
      </Key>
      <Forenames>D. W</Forenames>
      <PageNumber>11051</PageNumber>
    </MainItem>
  </ItemGroup>
  <ItemGroup>
    <MainItem>
      <Key>
        <KeyDitto>___ ___</KeyDitto>
      </Key>
      <Forenames>D. W. R.</Forenames>
      <PageNumber>12667</PageNumber>
    </MainItem>
  </ItemGroup>
  <ItemGroup>
    <MainItem>
      <Key>
        <KeyDitto>___ ___ ___</KeyDitto>
      </Key>
      <Forenames>E. F</Forenames>
      <PageNumber>13232</PageNumber>
    </MainItem>
  </ItemGroup>
  <ItemGroup>
    <MainItem>
      <Key>
        <KeyDitto>___ ___ ___ ___</KeyDitto>
      </Key>
      <Forenames>E. R</Forenames>
      <PageNumber>11849</PageNumber>
    </MainItem>
  </ItemGroup>
  <ItemGroup>
    <MainItem>
      <Key>
        <KeyDitto>___ ___</KeyDitto>
      </Key>
      <Forenames>F. A</Forenames>
      <PageNumber>11329</PageNumber>
    </MainItem>
  </ItemGroup>
  <ItemGroup>
    <MainItem>
      <Key>
        <KeyDitto>___ ___ ___ ___</KeyDitto>
      </Key>
      <Forenames>G. A</Forenames>
      <PageNumber>12403</PageNumber>
    </MainItem>
  </ItemGroup>
  <ItemGroup>
    <MainItem>
      <Key>
        <KeyDitto>___ ___ ___</KeyDitto>
      </Key>
      <Forenames>G. F</Forenames>
      <PageNumber>13916</PageNumber>
    </MainItem>
  </ItemGroup>
  <ItemGroup>
    <MainItem>
      <Key>
        <KeyDitto>___ ___ ___</KeyDitto>
      </Key>
      <Forenames>G. W</Forenames>
      <PageNumber>13916</PageNumber>
    </MainItem>
  </ItemGroup>
  <ItemGroup>
    <MainItem>
      <Key>
        <KeyDitto>___ ___</KeyDitto>
      </Key>
      <Forenames>I. D</Forenames>
      <PageNumber>11586</PageNumber>
    </MainItem>
  </ItemGroup>
  <ItemGroup>
    <MainItem>
      <Key>
        <KeyDitto>___ ___</KeyDitto>
      </Key>
      <Forenames>I. S</Forenames>
      <PageNumber>13513</PageNumber>
    </MainItem>
  </ItemGroup>
  <ItemGroup>
    <MainItem>
      <Key>
        <KeyDitto>___ ___ ___</KeyDitto>
      </Key>
      <Text>j</Text>
      <PageNumber>12120</PageNumber>
    </MainItem>
  </ItemGroup>
  <ItemGroup>
    <MainItem>
      <Key>
        <KeyDitto>___ ___</KeyDitto>
      </Key>
      <Forenames>J. A</Forenames>
      <PageNumber>13508</PageNumber>
    </MainItem>
  </ItemGroup>
  <ItemGroup>
    <MainItem>
      <Key>
        <KeyDitto>___ ___</KeyDitto>
      </Key>
      <Forenames>T. C</Forenames>
      <PageNumber>10776</PageNumber>
    </MainItem>
  </ItemGroup>
  <ItemGroup>
    <MainItem>
      <Key>
        <KeyDitto>___ ___</KeyDitto>
      </Key>
      <Forenames>T. J. F.</Forenames>
      <PageNumber>11322</PageNumber>
    </MainItem>
  </ItemGroup>
  <ItemGroup>
    <MainItem>
      <Key>
        <KeyDitto>___ ___</KeyDitto>
      </Key>
      <Forenames>J. M</Forenames>
      <PageNumber>11848</PageNumber>
    </MainItem>
  </ItemGroup>
  <ItemGroup>
    <MainItem>
      <Key>
        <KeyDitto>___ ___ ___</KeyDitto>
      </Key>
      <Forenames>J. R.</Forenames>
      <Text>(435475)</Text>
      <PageNumber>11585</PageNumber>
    </MainItem>
  </ItemGroup>
  <ItemGroup>
    <MainItem>
      <Key>
        <KeyDitto>___ ___</KeyDitto>
      </Key>
      <Forenames>J. J. R. R.</Forenames>
      <Text>(R.N.) (R.N.)</Text>
      <PageNumber>11840</PageNumber>
    </MainItem>
  </ItemGroup>
  <ItemGroup>
    <MainItem>
      <Key>
        <KeyDitto>___ ___ ___ .</KeyDitto>
      </Key>
      <Forenames>I. R.</Forenames>
      <Text>(400707)</Text>
      <PageNumber>13911</PageNumber>
    </MainItem>
  </ItemGroup>
  <ItemGroup>
    <MainItem>
      <Key>
        <KeyDitto>___ ___</KeyDitto>
      </Key>
      <Forenames>K. M</Forenames>
      <PageNumber>11844</PageNumber>
    </MainItem>
  </ItemGroup>
  <ItemGroup>
    <MainItem>
      <Key>
        <KeyDitto>___ ___ ___ ___</KeyDitto>
      </Key>
      <Forenames>L</Forenames>
      <PageNumber>11328</PageNumber>
    </MainItem>
  </ItemGroup>
  <ItemGroup>
    <MainItem>
      <Key>
        <KeyDitto>___</KeyDitto>
      </Key>
      <Forenames>L. R</Forenames>
      <PageNumber>11582</PageNumber>
    </MainItem>
  </ItemGroup>
  <ItemGroup>
    <MainItem>
      <Key>
        <KeyDitto>___ ___</KeyDitto>
      </Key>
      <Forenames>L. W.</Forenames>
      <PageNumber>12408</PageNumber>
    </MainItem>
  </ItemGroup>
  <ItemGroup>
    <MainItem>
      <Key>
        <KeyDitto>___ ___</KeyDitto>
      </Key>
      <Forenames>M. D. B.</Forenames>
      <PageNumber>13908</PageNumber>
    </MainItem>
  </ItemGroup>
  <ItemGroup>
    <MainItem>
      <Key>
        <KeyDitto>___ ___</KeyDitto>
      </Key>
      <Forenames>M. J</Forenames>
      <PageNumber>13912</PageNumber>
    </MainItem>
  </ItemGroup>
  <ItemGroup>
    <MainItem>
      <Key>
        <KeyDitto>___ ___ ___</KeyDitto>
      </Key>
      <Forenames>M. J. M.</Forenames>
      <PageNumber>11586</PageNumber>
    </MainItem>
  </ItemGroup>
  <ItemGroup>
    <MainItem>
      <Key>
        <KeyDitto>___ ___ ___</KeyDitto>
      </Key>
      <Forenames>M. L</Forenames>
      <PageNumber>11586</PageNumber>
    </MainItem>
  </ItemGroup>
  <ItemGroup>
    <MainItem>
      <Key>
        <KeyDitto>___ ___ ___</KeyDitto>
      </Key>
      <Forenames>M. M</Forenames>
      <PageNumber>12943</PageNumber>
    </MainItem>
  </ItemGroup>
  <ItemGroup>
    <MainItem>
      <Key>
        <KeyDitto>___ ___</KeyDitto>
      </Key>
      <Forenames>N. D</Forenames>
      <PageNumber>11322</PageNumber>
    </MainItem>
  </ItemGroup>
  <ItemGroup>
    <MainItem>
      <Key>
        <KeyDitto>___ ___</KeyDitto>
      </Key>
      <Forenames>P. B.</Forenames>
      <PageNumber>12406</PageNumber>
    </MainItem>
  </ItemGroup>
  <ItemGroup>
    <MainItem>
      <Key>
        <KeyDitto>___</KeyDitto>
      </Key>
      <Forenames>P. C. C.</Forenames>
      <PageNumber>12946</PageNumber>
    </MainItem>
  </ItemGroup>
  <ItemGroup>
    <MainItem>
      <Key>
        <KeyDitto>___</KeyDitto>
      </Key>
      <Forenames>P. R. M.</Forenames>
      <PageNumber>13916</PageNumber>
    </MainItem>
  </ItemGroup>
  <KeyDitto>___ ___ ___ ___</KeyDitto>
</Index>

